vjunit/__init__.py
vjunit/__main__.py
vjunit/template.html
vjunit/vjunit.py
vjunit-0.6.1.dist-info/DESCRIPTION.rst
vjunit-0.6.1.dist-info/METADATA
vjunit-0.6.1.dist-info/RECORD
vjunit-0.6.1.dist-info/WHEEL
vjunit-0.6.1.dist-info/entry_points.txt
vjunit-0.6.1.dist-info/metadata.json
vjunit-0.6.1.dist-info/top_level.txt
