Metadata-Version: 2.0
Name: vjunit
Version: 0.6.1
Summary: Generate html file from junit reports
Home-page: http://github.com/ahelsayd/vjunit
Author: Ahmed El-Sayed
Author-email: ahmed.m.elsayed93@gmail.com
License: UNKNOWN
Platform: UNKNOWN
Requires-Dist: jinja2
